{"PageNumber":40,"Angle":0,"RotatedAngle":0,"Height":1620,"Width":2880,"OriginHeight":0,"OriginWidth":0,"Elements":[{"Index":0,"Type":"title","Text":"#  IDS","Level":0,"Polygon":{"LeftBottom":{"X":219,"Y":289},"LeftTop":{"X":219,"Y":187},"RightBottom":{"X":398,"Y":289},"RightTop":{"X":398,"Y":187}},"InsetImageName":"","Elements":null,"ImagePath":"","group_id":-1,"group_type":""},{"Index":1,"Type":"title","Text":"##  ● Deep packet inspection:","Level":0,"Polygon":{"LeftBottom":{"X":219,"Y":527},"LeftTop":{"X":219,"Y":446},"RightBottom":{"X":1098,"Y":527},"RightTop":{"X":1098,"Y":446}},"InsetImageName":"","Elements":null,"ImagePath":"","group_id":-1,"group_type":""},{"Index":2,"Type":"paragraph","Text":"• look at packet contents (e.g., check strings in packet against database of known virus)","Level":0,"Polygon":{"LeftBottom":{"X":323,"Y":700},"LeftTop":{"X":323,"Y":546},"RightBottom":{"X":2474,"Y":700},"RightTop":{"X":2474,"Y":546}},"InsetImageName":"","Elements":null,"ImagePath":"","group_id":-1,"group_type":""},{"Index":3,"Type":"paragraph","Text":"● Examine correlation among multiple packets","Level":0,"Polygon":{"LeftBottom":{"X":323,"Y":789},"LeftTop":{"X":323,"Y":720},"RightBottom":{"X":1700,"Y":789},"RightTop":{"X":1700,"Y":720}},"InsetImageName":"","Elements":null,"ImagePath":"","group_id":-1,"group_type":""},{"Index":4,"Type":"paragraph","Text":"● port scanning, network mapping, DoS attack","Level":0,"Polygon":{"LeftBottom":{"X":432,"Y":875},"LeftTop":{"X":432,"Y":814},"RightBottom":{"X":1573,"Y":875},"RightTop":{"X":1573,"Y":814}},"InsetImageName":"","Elements":null,"ImagePath":"","group_id":-1,"group_type":""},{"Index":5,"Type":"paragraph","Text":"● Generate alerts when it observes potentially malicious traffic","Level":0,"Polygon":{"LeftBottom":{"X":219,"Y":989},"LeftTop":{"X":219,"Y":914},"RightBottom":{"X":2342,"Y":989},"RightTop":{"X":2342,"Y":914}},"InsetImageName":"","Elements":null,"ImagePath":"","group_id":-1,"group_type":""},{"Index":6,"Type":"paragraph","Text":"● Passive monitoring","Level":0,"Polygon":{"LeftBottom":{"X":219,"Y":1115},"LeftTop":{"X":219,"Y":1037},"RightBottom":{"X":925,"Y":1115},"RightTop":{"X":925,"Y":1037}},"InsetImageName":"","Elements":null,"ImagePath":"","group_id":-1,"group_type":""},{"Index":7,"Type":"title","Text":"##  ● Two main approaches:","Level":0,"Polygon":{"LeftBottom":{"X":219,"Y":1235},"LeftTop":{"X":219,"Y":1156},"RightBottom":{"X":1037,"Y":1235},"RightTop":{"X":1037,"Y":1156}},"InsetImageName":"","Elements":null,"ImagePath":"","group_id":-1,"group_type":""},{"Index":8,"Type":"paragraph","Text":"● Signature-based IDS","Level":0,"Polygon":{"LeftBottom":{"X":323,"Y":1331},"LeftTop":{"X":323,"Y":1258},"RightBottom":{"X":968,"Y":1331},"RightTop":{"X":968,"Y":1258}},"InsetImageName":"","Elements":null,"ImagePath":"","group_id":-1,"group_type":""},{"Index":9,"Type":"paragraph","Text":"● Anomaly-based/Heuristic-based IDS","Level":0,"Polygon":{"LeftBottom":{"X":323,"Y":1418},"LeftTop":{"X":323,"Y":1350},"RightBottom":{"X":1429,"Y":1418},"RightTop":{"X":1429,"Y":1350}},"InsetImageName":"","Elements":null,"ImagePath":"","group_id":-1,"group_type":""}]}