{"PageNumber":2,"Angle":0,"RotatedAngle":0,"Height":1620,"Width":2880,"OriginHeight":0,"OriginWidth":0,"Elements":[{"Index":0,"Type":"title","Text":"#  Cryptographic hash functions","Level":0,"Polygon":{"LeftBottom":{"X":216,"Y":310},"LeftTop":{"X":216,"Y":185},"RightBottom":{"X":1775,"Y":310},"RightTop":{"X":1775,"Y":185}},"InsetImageName":"","Elements":null,"ImagePath":"","group_id":-1,"group_type":""},{"Index":1,"Type":"paragraph","Text":"● To reduce the size of the message that Bob has to sign, we often use cryptographic hash functions, which are checksums on messages that have some additional useful properties:","Level":0,"Polygon":{"LeftBottom":{"X":225,"Y":708},"LeftTop":{"X":225,"Y":451},"RightBottom":{"X":2641,"Y":708},"RightTop":{"X":2641,"Y":451}},"InsetImageName":"","Elements":null,"ImagePath":"","group_id":-1,"group_type":""},{"Index":2,"Type":"paragraph","Text":"● One-way: it should be easy to compute Y=H(M), but hard to find M given only Y","Level":0,"Polygon":{"LeftBottom":{"X":335,"Y":870},"LeftTop":{"X":335,"Y":731},"RightBottom":{"X":2644,"Y":870},"RightTop":{"X":2644,"Y":731}},"InsetImageName":"","Elements":null,"ImagePath":"","group_id":-1,"group_type":""},{"Index":3,"Type":"paragraph","Text":"● Collision-resistant: it should be hard to find two messages, M and N, such that $H(M)=H(N)$","Level":0,"Polygon":{"LeftBottom":{"X":335,"Y":1052},"LeftTop":{"X":335,"Y":900},"RightBottom":{"X":2526,"Y":1052},"RightTop":{"X":2526,"Y":900}},"InsetImageName":"","Elements":null,"ImagePath":"","group_id":-1,"group_type":""},{"Index":4,"Type":"paragraph","Text":"• Examples: SHA-1, SHA-256","Level":0,"Polygon":{"LeftBottom":{"X":225,"Y":1169},"LeftTop":{"X":225,"Y":1091},"RightBottom":{"X":1184,"Y":1169},"RightTop":{"X":1184,"Y":1091}},"InsetImageName":"","Elements":null,"ImagePath":"","group_id":-1,"group_type":""}]}