{"PageNumber":26,"Angle":0,"RotatedAngle":0,"Height":1620,"Width":2880,"OriginHeight":0,"OriginWidth":0,"Elements":[{"Index":0,"Type":"title","Text":"#  Port Scanning","Level":0,"Polygon":{"LeftBottom":{"X":219,"Y":310},"LeftTop":{"X":219,"Y":180},"RightBottom":{"X":939,"Y":310},"RightTop":{"X":939,"Y":180}},"InsetImageName":"","Elements":null,"ImagePath":"","group_id":-1,"group_type":""},{"Index":1,"Type":"paragraph","Text":"● Once the IP address of the target is found, use the port scanning method to determine which ports are open in the host","Level":0,"Polygon":{"LeftBottom":{"X":216,"Y":644},"LeftTop":{"X":216,"Y":433},"RightBottom":{"X":1553,"Y":644},"RightTop":{"X":1553,"Y":433}},"InsetImageName":"","Elements":null,"ImagePath":"","group_id":-1,"group_type":""},{"Index":2,"Type":"paragraph","Text":"● Remember, ports are like doors of a house","Level":0,"Polygon":{"LeftBottom":{"X":216,"Y":744},"LeftTop":{"X":216,"Y":673},"RightBottom":{"X":1501,"Y":744},"RightTop":{"X":1501,"Y":673}},"InsetImageName":"","Elements":null,"ImagePath":"","group_id":-1,"group_type":""},{"Index":3,"Type":"paragraph","Text":"● Port scanning resembles knocking the doors to check which one is open","Level":0,"Polygon":{"LeftBottom":{"X":216,"Y":911},"LeftTop":{"X":216,"Y":770},"RightBottom":{"X":1553,"Y":911},"RightTop":{"X":1553,"Y":770}},"InsetImageName":"","Elements":null,"ImagePath":"","group_id":-1,"group_type":""},{"Index":4,"Type":"paragraph","Text":"● Some are well known open ports: web server:80, FTP: 21, SMTP: 25","Level":0,"Polygon":{"LeftBottom":{"X":216,"Y":1081},"LeftTop":{"X":216,"Y":942},"RightBottom":{"X":1389,"Y":1081},"RightTop":{"X":1389,"Y":942}},"InsetImageName":"","Elements":null,"ImagePath":"","group_id":-1,"group_type":""},{"Index":5,"Type":"paragraph","Text":"● However, some others ports also remain open for different applications","Level":0,"Polygon":{"LeftBottom":{"X":216,"Y":1253},"LeftTop":{"X":216,"Y":1109},"RightBottom":{"X":1443,"Y":1253},"RightTop":{"X":1443,"Y":1109}},"InsetImageName":"","Elements":null,"ImagePath":"","group_id":-1,"group_type":""},{"Index":6,"Type":"paragraph","Text":"● There are tools for checking an opening port:","Level":0,"Polygon":{"LeftBottom":{"X":216,"Y":1416},"LeftTop":{"X":216,"Y":1279},"RightBottom":{"X":1423,"Y":1416},"RightTop":{"X":1423,"Y":1279}},"InsetImageName":"","Elements":null,"ImagePath":"","group_id":-1,"group_type":""},{"Index":7,"Type":"paragraph","Text":"• nmap!","Level":0,"Polygon":{"LeftBottom":{"X":323,"Y":1493},"LeftTop":{"X":323,"Y":1429},"RightBottom":{"X":539,"Y":1493},"RightTop":{"X":539,"Y":1429}},"InsetImageName":"","Elements":null,"ImagePath":"","group_id":-1,"group_type":""},{"Index":8,"Type":"figure","Text":"","Level":0,"Polygon":{"LeftBottom":{"X":1680,"Y":1353},"LeftTop":{"X":1680,"Y":376},"RightBottom":{"X":2840,"Y":1353},"RightTop":{"X":2840,"Y":376}},"InsetImageName":"","Elements":[{"Index":0,"Type":"figure_text","Text":"|Time| |F|F1000|11000|13000|22000|50000|10000|25000|50000|10000|22000|14000|18000|24000|11000|22000|18000|11000|24000|18000|11000|22000|14000|11000|22000|18000|11000|22000|14000|11000|22000|11000|11000|22000|14000|11000|11000|22000|11000|11000|11000|22000|14000|11000|11000|11000|22000|11000|11000|11000|11000|11000|11000|11000|11000|11000|11000|11000|11000|11000|11000|11000|11000|11000|11000|11000|11000|11000|11000|11000|11000|11000|11000|11000|11000|11000|11000|11000|11000|11000|11000|11000|1100","Level":0,"Polygon":{"LeftBottom":{"X":1680,"Y":1353},"LeftTop":{"X":1680,"Y":376},"RightBottom":{"X":2840,"Y":1353},"RightTop":{"X":2840,"Y":376}},"InsetImageName":"","Elements":null,"ImagePath":"","group_id":0,"group_type":""}],"ImagePath":"images/2e6ab291ec45b6a8b100d1d0a902e671-image.png","group_id":-1,"group_type":""}]}