{"PageNumber":22,"Angle":0,"RotatedAngle":0,"Height":1620,"Width":2880,"OriginHeight":0,"OriginWidth":0,"Elements":[{"Index":0,"Type":"title","Text":"#  Hash Function: birthday attack","Level":0,"Polygon":{"LeftBottom":{"X":214,"Y":303},"LeftTop":{"X":214,"Y":180},"RightBottom":{"X":1829,"Y":303},"RightTop":{"X":1829,"Y":180}},"InsetImageName":"","Elements":null,"ImagePath":"","group_id":-1,"group_type":""},{"Index":1,"Type":"paragraph","Text":"● For Event 1, there are no previously analysed people","Level":0,"Polygon":{"LeftBottom":{"X":214,"Y":512},"LeftTop":{"X":214,"Y":430},"RightBottom":{"X":1924,"Y":512},"RightTop":{"X":1924,"Y":430}},"InsetImageName":"","Elements":null,"ImagePath":"","group_id":-1,"group_type":""},{"Index":2,"Type":"paragraph","Text":"● The probability, $P(1)$, that Person 1 does not share his/her birthday with previously analysed people is 1, or 100% or 365/365 ignoring leap years","Level":0,"Polygon":{"LeftBottom":{"X":320,"Y":657},"LeftTop":{"X":320,"Y":519},"RightBottom":{"X":2587,"Y":657},"RightTop":{"X":2587,"Y":519}},"InsetImageName":"","Elements":null,"ImagePath":"","group_id":-1,"group_type":""},{"Index":3,"Type":"paragraph","Text":"● For Event 2, the probability, $P(2)$, that Person 2 has a different birthday than Person 1 is 364/365","Level":0,"Polygon":{"LeftBottom":{"X":214,"Y":835},"LeftTop":{"X":214,"Y":679},"RightBottom":{"X":2500,"Y":835},"RightTop":{"X":2500,"Y":679}},"InsetImageName":"","Elements":null,"ImagePath":"","group_id":-1,"group_type":""},{"Index":4,"Type":"paragraph","Text":"● For Event 3, the probability, $P(3)$, that Person 3 has a different birthday than Person 1 and Person 2 is 363/365","Level":0,"Polygon":{"LeftBottom":{"X":214,"Y":1013},"LeftTop":{"X":214,"Y":859},"RightBottom":{"X":2500,"Y":1013},"RightTop":{"X":2500,"Y":859}},"InsetImageName":"","Elements":null,"ImagePath":"","group_id":-1,"group_type":""},{"Index":5,"Type":"paragraph","Text":"$$ \\begin{aligned} \\bullet P(A') &= \\frac{365}{365} \\times \\frac{364}{365} \\times \\frac{363}{365} \\times \\dots \\times \\frac{343}{365} \\\\ &= \\left(\\frac{1}{365}\\right)^{23} \\times (365 \\times 364 \\times \\dots \\times 343) \\\\ &= 0.492703 \\end{aligned} $$","Level":0,"Polygon":{"LeftBottom":{"X":214,"Y":1418},"LeftTop":{"X":214,"Y":1039},"RightBottom":{"X":1685,"Y":1418},"RightTop":{"X":1685,"Y":1039}},"InsetImageName":"","Elements":null,"ImagePath":"","group_id":-1,"group_type":""},{"Index":6,"Type":"paragraph","Text":"$$\\bullet P(A) = 1 - P(A') = 1 - 0.492703 = 0.507297 \\text{ or } 50.7\\% > 50\\%$$","Level":0,"Polygon":{"LeftBottom":{"X":214,"Y":1535},"LeftTop":{"X":214,"Y":1450},"RightBottom":{"X":2362,"Y":1535},"RightTop":{"X":2362,"Y":1450}},"InsetImageName":"","Elements":null,"ImagePath":"","group_id":-1,"group_type":""}]}